LICENSE
README.md
chialisp_builder.py
pyproject.toml
setup.py
chialisp_builder.egg-info/PKG-INFO
chialisp_builder.egg-info/SOURCES.txt
chialisp_builder.egg-info/dependency_links.txt
chialisp_builder.egg-info/requires.txt
chialisp_builder.egg-info/top_level.txt
tests/test_chialisp_build.py