Metadata-Version: 2.1
Name: chialisp-builder
Version: 0.1.1
Summary: Allow on-demand builds of chialisp with recursive dependency checking.
Author-email: Richard Kiss <him@richardkiss.com>
License: Copyright 2023 by Richard Kiss
License-File: LICENSE
Requires-Dist: clvm_tools_rs
Requires-Dist: runtime_builder>=0.1.2
